editscenario/__init__.py
editscenario/editscenario.py
editscenario/nml2xml.py
editscenario-0.11.7.dist-info/METADATA
editscenario-0.11.7.dist-info/WHEEL
editscenario-0.11.7.dist-info/entry_points.txt
editscenario-0.11.7.dist-info/top_level.txt
editscenario-0.11.7.dist-info/RECORD
