Metadata-Version: 2.1
Name: editscenario
Version: 0.11.7
Summary: Generate Fortran namelists from XML-files
Home-page: http://github.com/BoldingBruggeman/editscenario
Author: Jorn Bruggeman
Author-email: jorn@bolding-bruggeman.com
License: GPL
Platform: UNKNOWN
Classifier: Development Status :: 5 - Production/Stable
Classifier: Intended Audience :: Developers
Classifier: Topic :: Software Development :: Libraries :: Python Modules
Classifier: License :: OSI Approved :: GNU General Public License v2 (GPLv2)
Classifier: Programming Language :: Python :: 2 :: Only
Requires-Dist: xmlstore (>=0.9.9)
